haybox/__init__.py
haybox/haybox.py
haybox/proto/.git/FETCH_HEAD
haybox/proto/.git/HEAD
haybox/proto/.git/config
haybox/proto/.git/config.worktree
haybox/proto/.git/description
haybox/proto/.git/hooks/applypatch-msg.sample
haybox/proto/.git/hooks/commit-msg.sample
haybox/proto/.git/hooks/fsmonitor-watchman.sample
haybox/proto/.git/hooks/post-update.sample
haybox/proto/.git/hooks/pre-applypatch.sample
haybox/proto/.git/hooks/pre-commit.sample
haybox/proto/.git/hooks/pre-merge-commit.sample
haybox/proto/.git/hooks/pre-push.sample
haybox/proto/.git/hooks/pre-rebase.sample
haybox/proto/.git/hooks/pre-receive.sample
haybox/proto/.git/hooks/prepare-commit-msg.sample
haybox/proto/.git/hooks/push-to-checkout.sample
haybox/proto/.git/hooks/sendemail-validate.sample
haybox/proto/.git/hooks/update.sample
haybox/proto/.git/index
haybox/proto/.git/info/exclude
haybox/proto/.git/logs/HEAD
haybox/proto/.git/logs/refs/heads/main
haybox/proto/.git/logs/refs/remotes/origin/HEAD
haybox/proto/.git/logs/refs/remotes/origin/custom_mode_experimentation
haybox/proto/.git/logs/refs/remotes/origin/main
haybox/proto/.git/objects/pack/pack-cfe2f800bf3884cb34af5ad3b8ccddb30980126f.idx
haybox/proto/.git/objects/pack/pack-cfe2f800bf3884cb34af5ad3b8ccddb30980126f.pack
haybox/proto/.git/objects/pack/pack-cfe2f800bf3884cb34af5ad3b8ccddb30980126f.rev
haybox/proto/.git/refs/heads/main
haybox/proto/.git/refs/remotes/origin/HEAD
haybox/proto/.git/refs/remotes/origin/custom_mode_experimentation
haybox/proto/.git/refs/remotes/origin/main
haybox/proto/config.options
haybox/proto/config.proto
haybox/proto/config_pb2.py
haybox/proto/config_pb2.pyi
haybox/proto/library.json
haybox-0.1.5.dist-info/METADATA
haybox-0.1.5.dist-info/WHEEL
haybox-0.1.5.dist-info/RECORD
